{
  "order":{
    "monotouch_1.1.html":"MonoTouch 1.1",
    "monotouch_1.1.1.html":"MonoTouch 1.1.1",
    "monotouch_1.2.html":"MonoTouch 1.2",
    "monotouch_1.2_beta_1.html":"MonoTouch 1.2 Beta 1",
    "monotouch_1.3.html":"MonoTouch 1.3",
    "monotouch_1.4.html":"MonoTouch 1.4",
    "monotouch_1.4.100.html":"MonoTouch 1.4.100",
    "monotouch_1.4.101.html":"MonoTouch 1.4.101",
    "monotouch_1.4.102.html":"MonoTouch 1.4.102",
    "monotouch_1.4.4.html":"MonoTouch 1.4.4",
    "monotouch_1.4.5.html":"MonoTouch 1.4.5",
    "monotouch_1.4.6.html":"MonoTouch 1.4.6",
    "monotouch_1.4.99.html":"MonoTouch 1.4.99",
    "monotouch_1.5.html":"MonoTouch 1.5",
    "monotouch_1.9.1.html":"MonoTouch 1.9.1",
    "monotouch_1.9.2.html":"MonoTouch 1.9.2",
    "monotouch_1.9.3.html":"MonoTouch 1.9.3",
    "monotouch_1.9.4.html":"MonoTouch 1.9.4",
    "monotouch_1.9.5.html":"MonoTouch 1.9.5"
  }
}